compute_distance/__init__.py
compute_distance/cli.py
compute_distance/functions.py
compute_distance/py.typed
compute_distance-0.0.6.dist-info/LICENSE
compute_distance-0.0.6.dist-info/METADATA
compute_distance-0.0.6.dist-info/WHEEL
compute_distance-0.0.6.dist-info/entry_points.txt
compute_distance-0.0.6.dist-info/RECORD
