Metadata-Version: 2.1
Name: compute_distance
Version: 0.0.6
Summary: Compute distances and create TIF files
Home-page: https://MFStark.github.io/compute_distance
License: MIT
Author: Marcon
Author-email: mfikingas@gmail.com
Requires-Python: >=3.10,<4.0
Classifier: Development Status :: 4 - Beta
Classifier: Intended Audience :: Developers
Classifier: License :: OSI Approved :: MIT License
Classifier: Operating System :: OS Independent
Classifier: Programming Language :: Python
Classifier: Programming Language :: Python :: 3
Classifier: Programming Language :: Python :: 3.10
Classifier: Programming Language :: Python :: 3.11
Classifier: Programming Language :: Python :: 3.12
Classifier: Programming Language :: Python :: 3.7
Classifier: Programming Language :: Python :: 3.8
Classifier: Programming Language :: Python :: 3.9
Classifier: Topic :: Software Development :: Libraries :: Python Modules
Classifier: Typing :: Typed
Requires-Dist: affine (>=2.4.0,<3.0.0)
Requires-Dist: click
Requires-Dist: geopandas (>=0.14.1,<0.15.0)
Requires-Dist: matplotlib (>=3.8.2,<4.0.0)
Requires-Dist: numpy (>=1.26.2,<2.0.0)
Requires-Dist: pandas (>=2.1.3,<3.0.0)
Requires-Dist: rasterio (>=1.3.9,<2.0.0)
Requires-Dist: scipy (>=1.11.4,<2.0.0)
Requires-Dist: shapely (>=2.0.2,<3.0.0)
Project-URL: Documentation, https://MFStark.github.io/compute_distance
Project-URL: Repository, https://github.com/MFStark/compute_distance
